ccml2021/__init__.py
ccml2021/checker.py
ccml2021/gp.py
ccml2021-0.4.5.dist-info/METADATA
ccml2021-0.4.5.dist-info/WHEEL
ccml2021-0.4.5.dist-info/entry_points.txt
ccml2021-0.4.5.dist-info/RECORD
